intracluster_filtering/__init__.py
intracluster_filtering/data_selector.py
utils/__init__.py
intraclusterfiltering-1.1.0.dist-info/METADATA
intraclusterfiltering-1.1.0.dist-info/WHEEL
intraclusterfiltering-1.1.0.dist-info/top_level.txt
intraclusterfiltering-1.1.0.dist-info/RECORD
