Metadata-Version: 2.1
Name: intraclusterfiltering
Version: 1.1.0
Summary: Intra clustering outliers detector
Home-page: https://github.com/juanzamorai/intracluster-filtering
Author: Sebastian Jara, Juan Zamora, Pascal
Author-email: 
License: MIT
Requires-Dist: numpy ==1.25.2
Requires-Dist: scikit-learn
Requires-Dist: tensorflow ==2.10.0
Requires-Dist: keras ==2.10.0
Requires-Dist: protobuf <3.20,>=3.9.2
Requires-Dist: gast
Requires-Dist: astunparse
Requires-Dist: flatbuffers >=23.5.26
Requires-Dist: google-pasta >=0.1.1
Requires-Dist: libclang >=13.0.0
Requires-Dist: opt-einsum >=2.3.2
Requires-Dist: plotly
Requires-Dist: ml-dtypes ==0.3.1
Requires-Dist: seaborn
